CHANGES.rst
LICENSE.rst
README.rst
pyproject.toml
src/borgstore/__init__.py
src/borgstore/__main__.py
src/borgstore/_version.py
src/borgstore/constants.py
src/borgstore/store.py
src/borgstore.egg-info/PKG-INFO
src/borgstore.egg-info/SOURCES.txt
src/borgstore.egg-info/dependency_links.txt
src/borgstore.egg-info/requires.txt
src/borgstore.egg-info/top_level.txt
src/borgstore/backends/__init__.py
src/borgstore/backends/_base.py
src/borgstore/backends/errors.py
src/borgstore/backends/posixfs.py
src/borgstore/backends/rclone.py
src/borgstore/backends/s3.py
src/borgstore/backends/sftp.py
src/borgstore/utils/__init__.py
src/borgstore/utils/nesting.py