Metadata-Version: 2.4
Name: borgstore
Version: 0.2.0
Summary: key/value store
Author-email: Thomas Waldmann <tw@waldmann-edv.de>
License: BSD
Project-URL: Homepage, https://github.com/borgbackup/borgstore
Keywords: kv,key/value,store
Classifier: Development Status :: 3 - Alpha
Classifier: Intended Audience :: Developers
Classifier: License :: OSI Approved :: BSD License
Classifier: Operating System :: POSIX
Classifier: Programming Language :: Python
Classifier: Programming Language :: Python :: 3
Classifier: Programming Language :: Python :: 3.9
Classifier: Programming Language :: Python :: 3.10
Classifier: Programming Language :: Python :: 3.11
Classifier: Programming Language :: Python :: 3.12
Classifier: Programming Language :: Python :: 3.13
Classifier: Topic :: Software Development :: Libraries
Classifier: Topic :: Software Development :: Libraries :: Python Modules
Requires-Python: >=3.9
License-File: LICENSE.rst
Requires-Dist: requests>=2.25.1
Provides-Extra: sftp
Requires-Dist: paramiko>=1.9.1; extra == "sftp"
Provides-Extra: s3
Requires-Dist: boto3; extra == "s3"
Provides-Extra: none
Dynamic: license-file
